[{"CategoryProductionKeywords":[{"category":"51_Master Category","keyword":"Event","pkg_no":0,"prod_season_no":119884},{"category":"50_Master_Location","keyword":"Uptown","pkg_no":0,"prod_season_no":119884},{"category":"52_Center\/Department","keyword":"Simon","pkg_no":0,"prod_season_no":119884},{"category":"55_dd_Day Search","keyword":"Monday","pkg_no":0,"prod_season_no":119884},{"category":"55_dd_Day Search","keyword":"Weekday","pkg_no":0,"prod_season_no":119884},{"category":"56_dd_Time Search","keyword":"Evening","pkg_no":0,"prod_season_no":119884},{"category":"10_Product Type","keyword":"35 and Under Discount","pkg_no":0,"prod_season_no":119884},{"category":"10_Product Type","keyword":"Lecture","pkg_no":0,"prod_season_no":119884},{"category":"10_Product Type","keyword":"new just added","pkg_no":0,"prod_season_no":119884},{"category":"10a_dd_Age Levels","keyword":"Adults","pkg_no":0,"prod_season_no":119884},{"category":"10a_dd_Age Levels","keyword":"Teens","pkg_no":0,"prod_season_no":119884},{"category":"11_Subject:LecSeries","keyword":"all Culture and Ideas","pkg_no":0,"prod_season_no":119884},{"category":"11_Subject:special events","keyword":"Genius Festival","pkg_no":0,"prod_season_no":119884},{"category":"11_Subject:special events","keyword":"Seven Days Festival","pkg_no":0,"prod_season_no":119884},{"category":"14_dd_UpE Cal_Search","keyword":"Lectures & Conversations","pkg_no":0,"prod_season_no":119884}],"Description":null,"FirstDate":"\/Date(1457398800000-0500)\/","FuturePerformanceCount":1,"FuturePerformances":[{"days_of_week":"Monday","instructors":"","is_class":false,"is_event":true,"lowest_price":"$32.00","number_of_sessions":1,"perf_dt":"\/Date(1457398800000-0500)\/","perf_no":119885,"perf_start_to_end":"Mon, Mar 7, 2016, 8 pm","prod_no":119883,"thumbnail":null,"title":null}],"IsCYOPackage":false,"IsFixedPackage":false,"IsMultipleDatesTimes":false,"IsPackageOnly":false,"LastDate":"\/Date(1457398800000-0500)\/","LowestPrice":"$32.00","MainImage":"\/92streety\/media\/headshots\/_group\/lg\/g_030716_loeb_urry.jpg","MediumImage":"\/92streety\/media\/headshots\/_group\/MD\/g_030716_loeb_urry.jpg","NextPerformanceDateTime":"\/Date(1457398800000-0500)\/","NextPerformanceNumber":119885,"OnSale":true,"PackageNo":0,"PriorityRegMessage":"","PriorityRegRank":"","ProdSeasonDescription":null,"ProdSeasonInstructors":[],"ProdStatus":"","ProductionNumber":119883,"ProductionSeasonNumber":119884,"ShortDesc":"Two top astrophysicists explain why we are in the Golden Age of cosmological exploration.","SmallImage":"\/92streety\/media\/headshots\/_group\/SM\/g_030716_loeb_urry.jpg","ThisIsPartOfSeries":[],"ThumbnailImage":"\/92streety\/media\/headshots\/_group\/TB\/g_030716_loeb_urry.jpg","Title":"Seven Days of Genius: What’s Out There?","URL":"\/Event\/7-Days-Genius-What-s-Out-There"}]